{
  "book": "Job",
  "chapter": 3,
  "language": "hebrew",
  "version": "Hebrew",
  "verses": [
    {
      "verse": 1,
      "text": "אחרי כן פתח איוב את פי/הו ו/יקלל את יומ/ו"
    },
    {
      "verse": 2,
      "text": "ו/יען איוב ו/יאמר"
    },
    {
      "verse": 3,
      "text": "יאבד יום אולד ב/ו ו/ה/לילה אמר הרה גבר"
    },
    {
      "verse": 4,
      "text": "ה/יום ה/הוא יהי חשך אל ידרש/הו אלוה מ/מעל ו/אל תופע עלי/ו נהרה"
    },
    {
      "verse": 5,
      "text": "יגאל/הו חשך ו/צלמות תשכן עלי/ו עננה יבעת/הו כמרירי יום"
    },
    {
      "verse": 6,
      "text": "ה/לילה ה/הוא יקח/הו אפל אל יחד ב/ימי שנה ב/מספר ירחים אל יבא"
    },
    {
      "verse": 7,
      "text": "הנה ה/לילה ה/הוא יהי גלמוד אל תבא רננה ב/ו"
    },
    {
      "verse": 8,
      "text": "יקב/הו אררי יום ה/עתידים ערר לויתן"
    },
    {
      "verse": 9,
      "text": "יחשכו כוכבי נשפ/ו יקו ל/אור ו/אין ו/אל יראה ב/עפעפי שחר"
    },
    {
      "verse": 10,
      "text": "כי לא סגר דלתי בטנ/י ו/יסתר עמל מ/עינ/י"
    },
    {
      "verse": 11,
      "text": "ל/מה לא מ/רחם אמות מ/בטן יצאתי ו/אגוע"
    },
    {
      "verse": 12,
      "text": "מדוע קדמו/ני ברכים ו/מה שדים כי אינק"
    },
    {
      "verse": 13,
      "text": "כי עתה שכבתי ו/אשקוט ישנתי אז ינוח ל/י"
    },
    {
      "verse": 14,
      "text": "עם מלכים ו/יעצי ארץ ה/בנים חרבות ל/מו"
    },
    {
      "verse": 15,
      "text": "או עם שרים זהב ל/הם ה/ממלאים בתי/הם כסף"
    },
    {
      "verse": 16,
      "text": "או כ/נפל טמון לא אהיה כ/עללים לא ראו אור"
    },
    {
      "verse": 17,
      "text": "שם רשעים חדלו רגז ו/שם ינוחו יגיעי כח"
    },
    {
      "verse": 18,
      "text": "יחד אסירים שאננו לא שמעו קול נגש"
    },
    {
      "verse": 19,
      "text": "קטן ו/גדול שם הוא ו/עבד חפשי מ/אדני/ו"
    },
    {
      "verse": 20,
      "text": "ל/מה יתן ל/עמל אור ו/חיים ל/מרי נפש"
    },
    {
      "verse": 21,
      "text": "ה/מחכים ל/מות ו/אינ/נו ו/יחפר/הו מ/מטמונים"
    },
    {
      "verse": 22,
      "text": "ה/שמחים אלי גיל ישישו כי ימצאו קבר"
    },
    {
      "verse": 23,
      "text": "ל/גבר אשר דרכ/ו נסתרה ו/יסך אלוה בעד/ו"
    },
    {
      "verse": 24,
      "text": "כי ל/פני לחמ/י אנחת/י תבא ו/יתכו כ/מים שאגת/י"
    },
    {
      "verse": 25,
      "text": "כי פחד פחדתי ו/יאתי/ני ו/אשר יגרתי יבא ל/י"
    },
    {
      "verse": 26,
      "text": "לא שלותי ו/לא שקטתי ו/לא נחתי ו/יבא רגז"
    }
  ]
}