{
  "book": "Numbers",
  "chapter": 14,
  "language": "hebrew",
  "version": "Hebrew",
  "verses": [
    {
      "verse": 1,
      "text": "ו/תשא כל ה/עדה ו/יתנו את קול/ם ו/יבכו ה/עם ב/לילה ה/הוא"
    },
    {
      "verse": 2,
      "text": "ו/ילנו על משה ו/על אהרן כל בני ישראל ו/יאמרו אל/הם כל ה/עדה לו מתנו ב/ארץ מצרים או ב/מדבר ה/זה לו מתנו"
    },
    {
      "verse": 3,
      "text": "ו/ל/מה יהוה מביא את/נו אל ה/ארץ ה/זאת ל/נפל ב/חרב נשי/נו ו/טפ/נו יהיו ל/בז ה/לוא טוב ל/נו שוב מצרימ/ה"
    },
    {
      "verse": 4,
      "text": "ו/יאמרו איש אל אחי/ו נתנה ראש ו/נשובה מצרימ/ה"
    },
    {
      "verse": 5,
      "text": "ו/יפל משה ו/אהרן על פני/הם ל/פני כל קהל עדת בני ישראל"
    },
    {
      "verse": 6,
      "text": "ו/יהושע בן נון ו/כלב בן יפנה מן ה/תרים את ה/ארץ קרעו בגדי/הם"
    },
    {
      "verse": 7,
      "text": "ו/יאמרו אל כל עדת בני ישראל ל/אמר ה/ארץ אשר עברנו ב/ה ל/תור את/ה טובה ה/ארץ מאד מאד"
    },
    {
      "verse": 8,
      "text": "אם חפץ ב/נו יהוה ו/הביא את/נו אל ה/ארץ ה/זאת ו/נתנ/ה ל/נו ארץ אשר הוא זבת חלב ו/דבש"
    },
    {
      "verse": 9,
      "text": "אך ב/יהוה אל תמרדו ו/אתם אל תיראו את עם ה/ארץ כי לחמ/נו הם סר צל/ם מ/עלי/הם ו/יהוה את/נו אל תירא/ם"
    },
    {
      "verse": 10,
      "text": "ו/יאמרו כל ה/עדה ל/רגום את/ם ב/אבנים ו/כבוד יהוה נראה ב/אהל מועד אל כל בני ישראל"
    },
    {
      "verse": 11,
      "text": "ו/יאמר יהוה אל משה עד אנה ינאצ/ני ה/עם ה/זה ו/עד אנה לא יאמינו ב/י ב/כל ה/אתות אשר עשיתי ב/קרב/ו"
    },
    {
      "verse": 12,
      "text": "אכ/נו ב/דבר ו/אורש/נו ו/אעשה את/ך ל/גוי גדול ו/עצום ממ/נו"
    },
    {
      "verse": 13,
      "text": "ו/יאמר משה אל יהוה ו/שמעו מצרים כי העלית ב/כח/ך את ה/עם ה/זה מ/קרב/ו"
    },
    {
      "verse": 14,
      "text": "ו/אמרו אל יושב ה/ארץ ה/זאת שמעו כי אתה יהוה ב/קרב ה/עם ה/זה אשר עין ב/עין נראה אתה יהוה ו/עננ/ך עמד על/הם ו/ב/עמד ענן אתה הלך ל/פני/הם יומם ו/ב/עמוד אש לילה"
    },
    {
      "verse": 15,
      "text": "ו/המתה את ה/עם ה/זה כ/איש אחד ו/אמרו ה/גוים אשר שמעו את שמע/ך ל/אמר"
    },
    {
      "verse": 16,
      "text": "מ/בלתי יכלת יהוה ל/הביא את ה/עם ה/זה אל ה/ארץ אשר נשבע ל/הם ו/ישחט/ם ב/מדבר"
    },
    {
      "verse": 17,
      "text": "ו/עתה יגדל נא כח אדנ/י כ/אשר דברת ל/אמר"
    },
    {
      "verse": 18,
      "text": "יהוה ארך אפים ו/רב חסד נשא עון ו/פשע ו/נקה לא ינקה פקד עון אבות על בנים על שלשים ו/על רבעים"
    },
    {
      "verse": 19,
      "text": "סלח נא ל/עון ה/עם ה/זה כ/גדל חסד/ך ו/כ/אשר נשאתה ל/עם ה/זה מ/מצרים ו/עד הנה"
    },
    {
      "verse": 20,
      "text": "ו/יאמר יהוה סלחתי כ/דבר/ך"
    },
    {
      "verse": 21,
      "text": "ו/אולם חי אני ו/ימלא כבוד יהוה את כל ה/ארץ"
    },
    {
      "verse": 22,
      "text": "כי כל ה/אנשים ה/ראים את כבד/י ו/את אתת/י אשר עשיתי ב/מצרים ו/ב/מדבר ו/ינסו את/י זה עשר פעמים ו/לא שמעו ב/קול/י"
    },
    {
      "verse": 23,
      "text": "אם יראו את ה/ארץ אשר נשבעתי ל/אבת/ם ו/כל מנאצ/י לא יראו/ה"
    },
    {
      "verse": 24,
      "text": "ו/עבד/י כלב עקב היתה רוח אחרת עמ/ו ו/ימלא אחר/י ו/הביאתי/ו אל ה/ארץ אשר בא שמ/ה ו/זרע/ו יורש/נה"
    },
    {
      "verse": 25,
      "text": "ו/ה/עמלקי ו/ה/כנעני יושב ב/עמק מחר פנו ו/סעו ל/כם ה/מדבר דרך ים סוף"
    },
    {
      "verse": 26,
      "text": "ו/ידבר יהוה אל משה ו/אל אהרן ל/אמר"
    },
    {
      "verse": 27,
      "text": "עד מתי ל/עדה ה/רעה ה/זאת אשר המה מלינים על/י את תלנות בני ישראל אשר המה מלינים על/י שמעתי"
    },
    {
      "verse": 28,
      "text": "אמר אל/הם חי אני נאם יהוה אם לא כ/אשר דברתם ב/אזנ/י כן אעשה ל/כם"
    },
    {
      "verse": 29,
      "text": "ב/מדבר ה/זה יפלו פגרי/כם ו/כל פקדי/כם ל/כל מספר/כם מ/בן עשרים שנה ו/מעל/ה אשר הלינתם על/י"
    },
    {
      "verse": 30,
      "text": "אם אתם תבאו אל ה/ארץ אשר נשאתי את יד/י ל/שכן את/כם ב/ה כי אם כלב בן יפנה ו/יהושע בן נון"
    },
    {
      "verse": 31,
      "text": "ו/טפ/כם אשר אמרתם ל/בז יהיה ו/הביאתי את/ם ו/ידעו את ה/ארץ אשר מאסתם ב/ה"
    },
    {
      "verse": 32,
      "text": "ו/פגרי/כם אתם יפלו ב/מדבר ה/זה"
    },
    {
      "verse": 33,
      "text": "ו/בני/כם יהיו רעים ב/מדבר ארבעים שנה ו/נשאו את זנותי/כם עד תם פגרי/כם ב/מדבר"
    },
    {
      "verse": 34,
      "text": "ב/מספר ה/ימים אשר תרתם את ה/ארץ ארבעים יום יום ל/שנה יום ל/שנה תשאו את עונתי/כם ארבעים שנה ו/ידעתם את תנואת/י"
    },
    {
      "verse": 35,
      "text": "אני יהוה דברתי אם לא זאת אעשה ל/כל ה/עדה ה/רעה ה/זאת ה/נועדים על/י ב/מדבר ה/זה יתמו ו/שם ימתו"
    },
    {
      "verse": 36,
      "text": "ו/ה/אנשים אשר שלח משה ל/תור את ה/ארץ ו/ישבו ו/ילונו ו/ילינו עלי/ו את כל ה/עדה ל/הוציא דבה על ה/ארץ"
    },
    {
      "verse": 37,
      "text": "ו/ימתו ה/אנשים מוצאי דבת ה/ארץ רעה ב/מגפה ל/פני יהוה"
    },
    {
      "verse": 38,
      "text": "ו/יהושע בן נון ו/כלב בן יפנה חיו מן ה/אנשים ה/הם ה/הלכים ל/תור את ה/ארץ"
    },
    {
      "verse": 39,
      "text": "ו/ידבר משה את ה/דברים ה/אלה אל כל בני ישראל ו/יתאבלו ה/עם מאד"
    },
    {
      "verse": 40,
      "text": "ו/ישכמו ב/בקר ו/יעלו אל ראש ה/הר ל/אמר הנ/נו ו/עלינו אל ה/מקום אשר אמר יהוה כי חטאנו"
    },
    {
      "verse": 41,
      "text": "ו/יאמר משה ל/מה זה אתם עברים את פי יהוה ו/הוא לא תצלח"
    },
    {
      "verse": 42,
      "text": "אל תעלו כי אין יהוה ב/קרב/כם ו/לא תנגפו ל/פני איבי/כם"
    },
    {
      "verse": 43,
      "text": "כי ה/עמלקי ו/ה/כנעני שם ל/פני/כם ו/נפלתם ב/חרב כי על כן שבתם מ/אחרי יהוה ו/לא יהיה יהוה עמ/כם"
    },
    {
      "verse": 44,
      "text": "ו/יעפלו ל/עלות אל ראש ה/הר ו/ארון ברית יהוה ו/משה לא משו מ/קרב ה/מחנה"
    },
    {
      "verse": 45,
      "text": "ו/ירד ה/עמלקי ו/ה/כנעני ה/ישב ב/הר ה/הוא ו/יכו/ם ו/יכתו/ם עד ה/חרמה"
    }
  ]
}