{
  "book": "Ezekiel",
  "chapter": 37,
  "language": "hebrew",
  "version": "Hebrew",
  "verses": [
    {
      "verse": 1,
      "text": "היתה על/י יד יהוה ו/יוצא/ני ב/רוח יהוה ו/יניח/ני ב/תוך ה/בקעה ו/היא מלאה עצמות"
    },
    {
      "verse": 2,
      "text": "ו/העביר/ני עלי/הם סביב סביב ו/הנה רבות מאד על פני ה/בקעה ו/הנה יבשות מאד"
    },
    {
      "verse": 3,
      "text": "ו/יאמר אל/י בן אדם ה/תחיינה ה/עצמות ה/אלה ו/אמר אדנ/י יהוה אתה ידעת"
    },
    {
      "verse": 4,
      "text": "ו/יאמר אל/י הנבא על ה/עצמות ה/אלה ו/אמרת אלי/הם ה/עצמות ה/יבשות שמעו דבר יהוה"
    },
    {
      "verse": 5,
      "text": "כה אמר אדנ/י יהוה ל/עצמות ה/אלה הנה אני מביא ב/כם רוח ו/חייתם"
    },
    {
      "verse": 6,
      "text": "ו/נתתי עלי/כם גדים ו/העלתי עלי/כם בשר ו/קרמתי עלי/כם עור ו/נתתי ב/כם רוח ו/חייתם ו/ידעתם כי אני יהוה"
    },
    {
      "verse": 7,
      "text": "ו/נבאתי כ/אשר צויתי ו/יהי קול כ/הנבא/י ו/הנה רעש ו/תקרבו עצמות עצם אל עצמ/ו"
    },
    {
      "verse": 8,
      "text": "ו/ראיתי ו/הנה עלי/הם גדים ו/בשר עלה ו/יקרם עלי/הם עור מ/ל/מעל/ה ו/רוח אין ב/הם"
    },
    {
      "verse": 9,
      "text": "ו/יאמר אל/י הנבא אל ה/רוח הנבא בן אדם ו/אמרת אל ה/רוח כה אמר אדנ/י יהוה מ/ארבע רוחות באי ה/רוח ו/פחי ב/הרוגים ה/אלה ו/יחיו"
    },
    {
      "verse": 10,
      "text": "ו/הנבאתי כ/אשר צו/ני ו/תבוא ב/הם ה/רוח ו/יחיו ו/יעמדו על רגלי/הם חיל גדול מאד מאד"
    },
    {
      "verse": 11,
      "text": "ו/יאמר אל/י בן אדם ה/עצמות ה/אלה כל בית ישראל המה הנה אמרים יבשו עצמותי/נו ו/אבדה תקות/נו נגזרנו ל/נו"
    },
    {
      "verse": 12,
      "text": "ל/כן הנבא ו/אמרת אלי/הם כה אמר אדנ/י יהוה הנה אני פתח את קברותי/כם ו/העליתי את/כם מ/קברותי/כם עמ/י ו/הבאתי את/כם אל אדמת ישראל"
    },
    {
      "verse": 13,
      "text": "ו/ידעתם כי אני יהוה ב/פתח/י את קברותי/כם ו/ב/העלות/י את/כם מ/קברותי/כם עמ/י"
    },
    {
      "verse": 14,
      "text": "ו/נתתי רוח/י ב/כם ו/חייתם ו/הנחתי את/כם על אדמת/כם ו/ידעתם כי אני יהוה דברתי ו/עשיתי נאם יהוה"
    },
    {
      "verse": 15,
      "text": "ו/יהי דבר יהוה אל/י ל/אמר"
    },
    {
      "verse": 16,
      "text": "ו/אתה בן אדם קח ל/ך עץ אחד ו/כתב עלי/ו ל/יהודה ו/ל/בני ישראל חבר/ו חברי/ו ו/לקח עץ אחד ו/כתוב עלי/ו ל/יוסף עץ אפרים ו/כל בית ישראל חבר/ו חברי/ו"
    },
    {
      "verse": 17,
      "text": "ו/קרב את/ם אחד אל אחד ל/ך ל/עץ אחד ו/היו ל/אחדים ב/יד/ך"
    },
    {
      "verse": 18,
      "text": "ו/כ/אשר יאמרו אלי/ך בני עמ/ך ל/אמר ה/לוא תגיד ל/נו מה אלה ל/ך"
    },
    {
      "verse": 19,
      "text": "דבר אל/הם כה אמר אדנ/י יהוה הנה אני לקח את עץ יוסף אשר ב/יד אפרים ו/שבטי ישראל חבר/ו חברי/ו ו/נתתי אות/ם עלי/ו את עץ יהודה ו/עשית/ם ל/עץ אחד ו/היו אחד ב/יד/י"
    },
    {
      "verse": 20,
      "text": "ו/היו ה/עצים אשר תכתב עלי/הם ב/יד/ך ל/עיני/הם"
    },
    {
      "verse": 21,
      "text": "ו/דבר אלי/הם כה אמר אדנ/י יהוה הנה אני לקח את בני ישראל מ/בין ה/גוים אשר הלכו שם ו/קבצתי את/ם מ/סביב ו/הבאתי אות/ם אל אדמת/ם"
    },
    {
      "verse": 22,
      "text": "ו/עשיתי את/ם ל/גוי אחד ב/ארץ ב/הרי ישראל ו/מלך אחד יהיה ל/כל/ם ל/מלך ו/לא יהיה יהיו עוד ל/שני גוים ו/לא יחצו עוד ל/שתי ממלכות עוד"
    },
    {
      "verse": 23,
      "text": "ו/לא יטמאו עוד ב/גלולי/הם ו/ב/שקוצי/הם ו/ב/כל פשעי/הם ו/הושעתי את/ם מ/כל מושבתי/הם אשר חטאו ב/הם ו/טהרתי אות/ם ו/היו ל/י ל/עם ו/אני אהיה ל/הם ל/אלהים"
    },
    {
      "verse": 24,
      "text": "ו/עבד/י דוד מלך עלי/הם ו/רועה אחד יהיה ל/כל/ם ו/ב/משפט/י ילכו ו/חקת/י ישמרו ו/עשו אות/ם"
    },
    {
      "verse": 25,
      "text": "ו/ישבו על ה/ארץ אשר נתתי ל/עבד/י ל/יעקב אשר ישבו ב/ה אבותי/כם ו/ישבו עלי/ה המה ו/בני/הם ו/בני בני/הם עד עולם ו/דוד עבד/י נשיא ל/הם ל/עולם"
    },
    {
      "verse": 26,
      "text": "ו/כרתי ל/הם ברית שלום ברית עולם יהיה אות/ם ו/נתתי/ם ו/הרביתי אות/ם ו/נתתי את מקדש/י ב/תוכ/ם ל/עולם"
    },
    {
      "verse": 27,
      "text": "ו/היה משכנ/י עלי/הם ו/הייתי ל/הם ל/אלהים ו/המה יהיו ל/י ל/עם"
    },
    {
      "verse": 28,
      "text": "ו/ידעו ה/גוים כי אני יהוה מקדש את ישראל ב/היות מקדש/י ב/תוכ/ם ל/עולם"
    }
  ]
}