{
  "book": "Psalms",
  "chapter": 14,
  "language": "hebrew",
  "version": "Hebrew",
  "verses": [
    {
      "verse": 1,
      "text": "ל/מנצח ל/דוד אמר נבל ב/לב/ו אין אלהים השחיתו התעיבו עלילה אין עשה טוב"
    },
    {
      "verse": 2,
      "text": "יהוה מ/שמים השקיף על בני אדם ל/ראות ה/יש משכיל דרש את אלהים"
    },
    {
      "verse": 3,
      "text": "ה/כל סר יחדו נאלחו אין עשה טוב אין גם אחד"
    },
    {
      "verse": 4,
      "text": "ה/לא ידעו כל פעלי און אכלי עמ/י אכלו לחם יהוה לא קראו"
    },
    {
      "verse": 5,
      "text": "שם פחדו פחד כי אלהים ב/דור צדיק"
    },
    {
      "verse": 6,
      "text": "עצת עני תבישו כי יהוה מחס/הו"
    },
    {
      "verse": 7,
      "text": "מי יתן מ/ציון ישועת ישראל ב/שוב יהוה שבות עמ/ו יגל יעקב ישמח ישראל"
    }
  ]
}