{
  "book": "1 Samuel",
  "chapter": 20,
  "language": "hebrew",
  "version": "Hebrew",
  "verses": [
    {
      "verse": 1,
      "text": "ו/יברח דוד מ/נוות מ/ניות ב/רמה ו/יבא ו/יאמר ל/פני יהונתן מה עשיתי מה עונ/י ו/מה חטאת/י ל/פני אבי/ך כי מבקש את נפש/י"
    },
    {
      "verse": 2,
      "text": "ו/יאמר ל/ו חליל/ה לא תמות הנה ל/ו עשה לא יעשה אב/י דבר גדול או דבר קטן ו/לא יגלה את אזנ/י ו/מדוע יסתיר אב/י ממ/ני את ה/דבר ה/זה אין זאת"
    },
    {
      "verse": 3,
      "text": "ו/ישבע עוד דוד ו/יאמר ידע ידע אבי/ך כי מצאתי חן ב/עיני/ך ו/יאמר אל ידע זאת יהונתן פן יעצב ו/אולם חי יהוה ו/חי נפש/ך כי כ/פשע בינ/י ו/בין ה/מות"
    },
    {
      "verse": 4,
      "text": "ו/יאמר יהונתן אל דוד מה תאמר נפש/ך ו/אעשה ל/ך"
    },
    {
      "verse": 5,
      "text": "ו/יאמר דוד אל יהונתן הנה חדש מחר ו/אנכי ישב אשב עם ה/מלך ל/אכול ו/שלחת/ני ו/נסתרתי ב/שדה עד ה/ערב ה/שלשית"
    },
    {
      "verse": 6,
      "text": "אם פקד יפקד/ני אבי/ך ו/אמרת נשאל נשאל ממ/ני דוד ל/רוץ בית לחם עיר/ו כי זבח ה/ימים שם ל/כל ה/משפחה"
    },
    {
      "verse": 7,
      "text": "אם כה יאמר טוב שלום ל/עבד/ך ו/אם חרה יחרה ל/ו דע כי כלתה ה/רעה מ/עמ/ו"
    },
    {
      "verse": 8,
      "text": "ו/עשית חסד על עבד/ך כי ב/ברית יהוה הבאת את עבד/ך עמ/ך ו/אם יש ב/י עון המית/ני אתה ו/עד אבי/ך ל/מה זה תביא/ני"
    },
    {
      "verse": 9,
      "text": "ו/יאמר יהונתן חליל/ה ל/ך כי אם ידע אדע כי כלתה ה/רעה מ/עם אב/י ל/בוא עלי/ך ו/לא את/ה אגיד ל/ך"
    },
    {
      "verse": 10,
      "text": "ו/יאמר דוד אל יהונתן מי יגיד ל/י או מה יענ/ך אבי/ך קשה"
    },
    {
      "verse": 11,
      "text": "ו/יאמר יהונתן אל דוד לכ/ה ו/נצא ה/שדה ו/יצאו שני/הם ה/שדה"
    },
    {
      "verse": 12,
      "text": "ו/יאמר יהונתן אל דוד יהוה אלהי ישראל כי אחקר את אב/י כ/עת מחר ה/שלשית ו/הנה טוב אל דוד ו/לא אז אשלח אלי/ך ו/גליתי את אזנ/ך"
    },
    {
      "verse": 13,
      "text": "כה יעשה יהוה ל/יהונתן ו/כה יסיף כי ייטב אל אב/י את ה/רעה עלי/ך ו/גליתי את אזנ/ך ו/שלחתי/ך ו/הלכת ל/שלום ו/יהי יהוה עמ/ך כ/אשר היה עם אב/י"
    },
    {
      "verse": 14,
      "text": "ו/לא אם עוד/ני חי ו/לא תעשה עמד/י חסד יהוה ו/לא אמות"
    },
    {
      "verse": 15,
      "text": "ו/לא תכרת את חסד/ך מ/עם בית/י עד עולם ו/לא ב/הכרת יהוה את איבי דוד איש מ/על פני ה/אדמה"
    },
    {
      "verse": 16,
      "text": "ו/יכרת יהונתן עם בית דוד ו/בקש יהוה מ/יד איבי דוד"
    },
    {
      "verse": 17,
      "text": "ו/יוסף יהונתן ל/השביע את דוד ב/אהבת/ו את/ו כי אהבת נפש/ו אהב/ו"
    },
    {
      "verse": 18,
      "text": "ו/יאמר ל/ו יהונתן מחר חדש ו/נפקדת כי יפקד מושב/ך"
    },
    {
      "verse": 19,
      "text": "ו/שלשת תרד מאד ו/באת אל ה/מקום אשר נסתרת שם ב/יום ה/מעשה ו/ישבת אצל ה/אבן ה/אזל"
    },
    {
      "verse": 20,
      "text": "ו/אני שלשת ה/חצים צד/ה אורה ל/שלח ל/י ל/מטרה"
    },
    {
      "verse": 21,
      "text": "ו/הנה אשלח את ה/נער לך מצא את ה/חצים אם אמר אמר ל/נער הנה ה/חצים ממ/ך ו/הנה קח/נו ו/בא/ה כי שלום ל/ך ו/אין דבר חי יהוה"
    },
    {
      "verse": 22,
      "text": "ו/אם כה אמר ל/עלם הנה ה/חצים ממ/ך ו/הלאה לך כי שלח/ך יהוה"
    },
    {
      "verse": 23,
      "text": "ו/ה/דבר אשר דברנו אני ו/אתה הנה יהוה בינ/י ו/בינ/ך עד עולם"
    },
    {
      "verse": 24,
      "text": "ו/יסתר דוד ב/שדה ו/יהי ה/חדש ו/ישב ה/מלך על אל ה/לחם ל/אכול"
    },
    {
      "verse": 25,
      "text": "ו/ישב ה/מלך על מושב/ו כ/פעם ב/פעם אל מושב ה/קיר ו/יקם יהונתן ו/ישב אבנר מ/צד שאול ו/יפקד מקום דוד"
    },
    {
      "verse": 26,
      "text": "ו/לא דבר שאול מאומה ב/יום ה/הוא כי אמר מקרה הוא בלתי טהור הוא כי לא טהור"
    },
    {
      "verse": 27,
      "text": "ו/יהי מ/מחרת ה/חדש ה/שני ו/יפקד מקום דוד ו/יאמר שאול אל יהונתן בנ/ו מדוע לא בא בן ישי גם תמול גם ה/יום אל ה/לחם"
    },
    {
      "verse": 28,
      "text": "ו/יען יהונתן את שאול נשאל נשאל דוד מ/עמד/י עד בית לחם"
    },
    {
      "verse": 29,
      "text": "ו/יאמר שלח/ני נא כי זבח משפחה ל/נו ב/עיר ו/הוא צוה ל/י אח/י ו/עתה אם מצאתי חן ב/עיני/ך אמלטה נא ו/אראה את אח/י על כן לא בא אל שלחן ה/מלך"
    },
    {
      "verse": 30,
      "text": "ו/יחר אף שאול ב/יהונתן ו/יאמר ל/ו בן נעות ה/מרדות ה/לוא ידעתי כי בחר אתה ל/בן ישי ל/בשת/ך ו/ל/בשת ערות אמ/ך"
    },
    {
      "verse": 31,
      "text": "כי כל ה/ימים אשר בן ישי חי על ה/אדמה לא תכון אתה ו/מלכות/ך ו/עתה שלח ו/קח את/ו אל/י כי בן מות הוא"
    },
    {
      "verse": 32,
      "text": "ו/יען יהונתן את שאול אבי/ו ו/יאמר אלי/ו ל/מה יומת מה עשה"
    },
    {
      "verse": 33,
      "text": "ו/יטל שאול את ה/חנית עלי/ו ל/הכת/ו ו/ידע יהונתן כי כלה היא מ/עם אבי/ו ל/המית את דוד"
    },
    {
      "verse": 34,
      "text": "ו/יקם יהונתן מ/עם ה/שלחן ב/חרי אף ו/לא אכל ב/יום ה/חדש ה/שני לחם כי נעצב אל דוד כי הכלמ/ו אבי/ו"
    },
    {
      "verse": 35,
      "text": "ו/יהי ב/בקר ו/יצא יהונתן ה/שדה ל/מועד דוד ו/נער קטן עמ/ו"
    },
    {
      "verse": 36,
      "text": "ו/יאמר ל/נער/ו רץ מצא נא את ה/חצים אשר אנכי מורה ה/נער רץ ו/הוא ירה ה/חצי ל/העבר/ו"
    },
    {
      "verse": 37,
      "text": "ו/יבא ה/נער עד מקום ה/חצי אשר ירה יהונתן ו/יקרא יהונתן אחרי ה/נער ו/יאמר ה/לוא ה/חצי ממ/ך ו/הלאה"
    },
    {
      "verse": 38,
      "text": "ו/יקרא יהונתן אחרי ה/נער מהרה חוש/ה אל תעמד ו/ילקט נער יהונתן את ה/חצי ה/חצים ו/יבא אל אדני/ו"
    },
    {
      "verse": 39,
      "text": "ו/ה/נער לא ידע מאומה אך יהונתן ו/דוד ידעו את ה/דבר"
    },
    {
      "verse": 40,
      "text": "ו/יתן יהונתן את כלי/ו אל ה/נער אשר ל/ו ו/יאמר ל/ו לך הביא ה/עיר"
    },
    {
      "verse": 41,
      "text": "ה/נער בא ו/דוד קם מ/אצל ה/נגב ו/יפל ל/אפי/ו ארצ/ה ו/ישתחו שלש פעמים ו/ישקו איש את רע/הו ו/יבכו איש את רע/הו עד דוד הגדיל"
    },
    {
      "verse": 42,
      "text": "ו/יקם ו/ילך ו/יהונתן בא ה/עיר"
    }
  ]
}