{
  "book": "2 Chronicles",
  "chapter": 20,
  "language": "hebrew",
  "version": "Hebrew",
  "verses": [
    {
      "verse": 1,
      "text": "ו/יהי אחרי כן באו בני מואב ו/בני עמון ו/עמ/הם מ/ה/עמונים על יהושפט ל/מלחמה"
    },
    {
      "verse": 2,
      "text": "ו/יבאו ו/יגידו ל/יהושפט ל/אמר בא עלי/ך המון רב מ/עבר ל/ים מ/ארם ו/הנ/ם ב/חצצון תמר היא עין גדי"
    },
    {
      "verse": 3,
      "text": "ו/ירא ו/יתן יהושפט את פני/ו ל/דרוש ל/יהוה ו/יקרא צום על כל יהודה"
    },
    {
      "verse": 4,
      "text": "ו/יקבצו יהודה ל/בקש מ/יהוה גם מ/כל ערי יהודה באו ל/בקש את יהוה"
    },
    {
      "verse": 5,
      "text": "ו/יעמד יהושפט ב/קהל יהודה ו/ירושלם ב/בית יהוה ל/פני ה/חצר ה/חדשה"
    },
    {
      "verse": 6,
      "text": "ו/יאמר יהוה אלהי אבתי/נו ה/לא אתה הוא אלהים ב/שמים ו/אתה מושל ב/כל ממלכות ה/גוים ו/ב/יד/ך כח ו/גבורה ו/אין עמ/ך ל/התיצב"
    },
    {
      "verse": 7,
      "text": "ה/לא אתה אלהי/נו הורשת את ישבי ה/ארץ ה/זאת מ/ל/פני עמ/ך ישראל ו/תתנ/ה ל/זרע אברהם אהב/ך ל/עולם"
    },
    {
      "verse": 8,
      "text": "ו/ישבו ב/ה ו/יבנו ל/ך ב/ה מקדש ל/שמ/ך ל/אמר"
    },
    {
      "verse": 9,
      "text": "אם תבוא עלי/נו רעה חרב שפוט ו/דבר ו/רעב נעמדה ל/פני ה/בית ה/זה ו/ל/פני/ך כי שמ/ך ב/בית ה/זה ו/נזעק אלי/ך מ/צרת/נו ו/תשמע ו/תושיע"
    },
    {
      "verse": 10,
      "text": "ו/עתה הנה בני עמון ו/מואב ו/הר שעיר אשר לא נתתה ל/ישראל ל/בוא ב/הם ב/בא/ם מ/ארץ מצרים כי סרו מ/עלי/הם ו/לא השמידו/ם"
    },
    {
      "verse": 11,
      "text": "ו/הנה הם גמלים עלי/נו ל/בוא ל/גרש/נו מ/ירשת/ך אשר הורשת/נו"
    },
    {
      "verse": 12,
      "text": "אלהי/נו ה/לא תשפט ב/ם כי אין ב/נו כח ל/פני ה/המון ה/רב ה/זה ה/בא עלי/נו ו/אנחנו לא נדע מה נעשה כי עלי/ך עיני/נו"
    },
    {
      "verse": 13,
      "text": "ו/כל יהודה עמדים ל/פני יהוה גם טפ/ם נשי/הם ו/בני/הם"
    },
    {
      "verse": 14,
      "text": "ו/יחזיאל בן זכריהו בן בניה בן יעיאל בן מתניה ה/לוי מן בני אסף היתה עלי/ו רוח יהוה ב/תוך ה/קהל"
    },
    {
      "verse": 15,
      "text": "ו/יאמר הקשיבו כל יהודה ו/ישבי ירושלם ו/ה/מלך יהושפט כה אמר יהוה ל/כם אתם אל תיראו ו/אל תחתו מ/פני ה/המון ה/רב ה/זה כי לא ל/כם ה/מלחמה כי ל/אלהים"
    },
    {
      "verse": 16,
      "text": "מחר רדו עלי/הם הנ/ם עלים ב/מעלה ה/ציץ ו/מצאתם את/ם ב/סוף ה/נחל פני מדבר ירואל"
    },
    {
      "verse": 17,
      "text": "לא ל/כם ל/הלחם ב/זאת התיצבו עמדו ו/ראו את ישועת יהוה עמ/כם יהודה ו/ירושלם אל תיראו ו/אל תחתו מחר צאו ל/פני/הם ו/יהוה עמ/כם"
    },
    {
      "verse": 18,
      "text": "ו/יקד יהושפט אפים ארצ/ה ו/כל יהודה ו/ישבי ירושלם נפלו ל/פני יהוה ל/השתחות ל/יהוה"
    },
    {
      "verse": 19,
      "text": "ו/יקמו ה/לוים מן בני ה/קהתים ו/מן בני ה/קרחים ל/הלל ל/יהוה אלהי ישראל ב/קול גדול ל/מעל/ה"
    },
    {
      "verse": 20,
      "text": "ו/ישכימו ב/בקר ו/יצאו ל/מדבר תקוע ו/ב/צאת/ם עמד יהושפט ו/יאמר שמעו/ני יהודה ו/ישבי ירושלם האמינו ב/יהוה אלהי/כם ו/תאמנו האמינו ב/נביאי/ו ו/הצליחו"
    },
    {
      "verse": 21,
      "text": "ו/יועץ אל ה/עם ו/יעמד משררים ל/יהוה ו/מהללים ל/הדרת קדש ב/צאת ל/פני ה/חלוץ ו/אמרים הודו ל/יהוה כי ל/עולם חסד/ו"
    },
    {
      "verse": 22,
      "text": "ו/ב/עת החלו ב/רנה ו/תהלה נתן יהוה מארבים על בני עמון מואב ו/הר שעיר ה/באים ל/יהודה ו/ינגפו"
    },
    {
      "verse": 23,
      "text": "ו/יעמדו בני עמון ו/מואב על ישבי הר שעיר ל/החרים ו/ל/השמיד ו/כ/כלות/ם ב/יושבי שעיר עזרו איש ב/רע/הו ל/משחית"
    },
    {
      "verse": 24,
      "text": "ו/יהודה בא על ה/מצפה ל/מדבר ו/יפנו אל ה/המון ו/הנ/ם פגרים נפלים ארצ/ה ו/אין פליטה"
    },
    {
      "verse": 25,
      "text": "ו/יבא יהושפט ו/עמ/ו ל/בז את שלל/ם ו/ימצאו ב/הם ל/רב ו/רכוש ו/פגרים ו/כלי חמדות ו/ינצלו ל/הם ל/אין משא ו/יהיו ימים שלושה בזזים את ה/שלל כי רב הוא"
    },
    {
      "verse": 26,
      "text": "ו/ב/יום ה/רבעי נקהלו ל/עמק ברכה כי שם ברכו את יהוה על כן קראו את שם ה/מקום ה/הוא עמק ברכה עד ה/יום"
    },
    {
      "verse": 27,
      "text": "ו/ישבו כל איש יהודה ו/ירושלם ו/יהושפט ב/ראש/ם ל/שוב אל ירושלם ב/שמחה כי שמח/ם יהוה מ/אויבי/הם"
    },
    {
      "verse": 28,
      "text": "ו/יבאו ירושלם ב/נבלים ו/ב/כנרות ו/ב/חצצרות אל בית יהוה"
    },
    {
      "verse": 29,
      "text": "ו/יהי פחד אלהים על כל ממלכות ה/ארצות ב/שמע/ם כי נלחם יהוה עם אויבי ישראל"
    },
    {
      "verse": 30,
      "text": "ו/תשקט מלכות יהושפט ו/ינח ל/ו אלהי/ו מ/סביב"
    },
    {
      "verse": 31,
      "text": "ו/ימלך יהושפט על יהודה בן שלשים ו/חמש שנה ב/מלכ/ו ו/עשרים ו/חמש שנה מלך ב/ירושלם ו/שם אמ/ו עזובה בת שלחי"
    },
    {
      "verse": 32,
      "text": "ו/ילך ב/דרך אבי/ו אסא ו/לא סר ממ/נה ל/עשות ה/ישר ב/עיני יהוה"
    },
    {
      "verse": 33,
      "text": "אך ה/במות לא סרו ו/עוד ה/עם לא הכינו לבב/ם ל/אלהי אבתי/הם"
    },
    {
      "verse": 34,
      "text": "ו/יתר דברי יהושפט ה/ראשנים ו/ה/אחרנים הנ/ם כתובים ב/דברי יהוא בן חנני אשר העלה על ספר מלכי ישראל"
    },
    {
      "verse": 35,
      "text": "ו/אחרי כן אתחבר יהושפט מלך יהודה עם אחזיה מלך ישראל הוא הרשיע ל/עשות"
    },
    {
      "verse": 36,
      "text": "ו/יחבר/הו עמ/ו ל/עשות אניות ל/לכת תרשיש ו/יעשו אניות ב/עציון גבר"
    },
    {
      "verse": 37,
      "text": "ו/יתנבא אליעזר בן דדוהו מ/מרשה על יהושפט ל/אמר כ/התחבר/ך עם אחזיהו פרץ יהוה את מעשי/ך ו/ישברו אניות ו/לא עצרו ל/לכת אל תרשיש"
    }
  ]
}