{
  "book": "Zechariah",
  "chapter": 11,
  "language": "hebrew",
  "version": "Hebrew",
  "verses": [
    {
      "verse": 1,
      "text": "פתח לבנון דלתי/ך ו/תאכל אש ב/ארזי/ך"
    },
    {
      "verse": 2,
      "text": "הילל ברוש כי נפל ארז אשר אדרים שדדו הילילו אלוני בשן כי ירד יער ה/בצור ה/בציר"
    },
    {
      "verse": 3,
      "text": "קול יללת ה/רעים כי שדדה אדרת/ם קול שאגת כפירים כי שדד גאון ה/ירדן"
    },
    {
      "verse": 4,
      "text": "כה אמר יהוה אלה/י רעה את צאן ה/הרגה"
    },
    {
      "verse": 5,
      "text": "אשר קני/הן יהרג/ן ו/לא יאשמו ו/מכרי/הן יאמר ברוך יהוה ו/אעשר ו/רעי/הם לא יחמול עלי/הן"
    },
    {
      "verse": 6,
      "text": "כי לא אחמול עוד על ישבי ה/ארץ נאם יהוה ו/הנה אנכי ממציא את ה/אדם איש ב/יד רע/הו ו/ב/יד מלכ/ו ו/כתתו את ה/ארץ ו/לא אציל מ/יד/ם"
    },
    {
      "verse": 7,
      "text": "ו/ארעה את צאן ה/הרגה ל/כן עניי ה/צאן ו/אקח ל/י שני מקלות ל/אחד קראתי נעם ו/ל/אחד קראתי חבלים ו/ארעה את ה/צאן"
    },
    {
      "verse": 8,
      "text": "ו/אכחד את שלשת ה/רעים ב/ירח אחד ו/תקצר נפש/י ב/הם ו/גם נפש/ם בחלה ב/י"
    },
    {
      "verse": 9,
      "text": "ו/אמר לא ארעה את/כם ה/מתה תמות ו/ה/נכחדת תכחד ו/ה/נשארות תאכלנה אשה את בשר רעות/ה"
    },
    {
      "verse": 10,
      "text": "ו/אקח את מקל/י את נעם ו/אגדע את/ו ל/הפיר את ברית/י אשר כרתי את כל ה/עמים"
    },
    {
      "verse": 11,
      "text": "ו/תפר ב/יום ה/הוא ו/ידעו כן עניי ה/צאן ה/שמרים את/י כי דבר יהוה הוא"
    },
    {
      "verse": 12,
      "text": "ו/אמר אלי/הם אם טוב ב/עיני/כם הבו שכר/י ו/אם לא חדלו ו/ישקלו את שכר/י שלשים כסף"
    },
    {
      "verse": 13,
      "text": "ו/יאמר יהוה אל/י השליכ/הו אל ה/יוצר אדר ה/יקר אשר יקרתי מ/עלי/הם ו/אקח/ה שלשים ה/כסף ו/אשליך את/ו בית יהוה אל ה/יוצר"
    },
    {
      "verse": 14,
      "text": "ו/אגדע את מקל/י ה/שני את ה/חבלים ל/הפר את ה/אחוה בין יהודה ו/בין ישראל"
    },
    {
      "verse": 15,
      "text": "ו/יאמר יהוה אל/י עוד קח ל/ך כלי רעה אולי"
    },
    {
      "verse": 16,
      "text": "כי הנה אנכי מקים רעה ב/ארץ ה/נכחדות לא יפקד ה/נער לא יבקש ו/ה/נשברת לא ירפא ה/נצבה לא יכלכל ו/בשר ה/בריאה יאכל ו/פרסי/הן יפרק"
    },
    {
      "verse": 17,
      "text": "הוי רעי ה/אליל עזבי ה/צאן חרב על זרוע/ו ו/על עין ימינ/ו זרע/ו יבוש תיבש ו/עין ימינ/ו כהה תכהה"
    }
  ]
}