{
  "book": "Exodus",
  "chapter": 11,
  "language": "hebrew",
  "version": "Hebrew",
  "verses": [
    {
      "verse": 1,
      "text": "ו/יאמר יהוה אל משה עוד נגע אחד אביא על פרעה ו/על מצרים אחרי כן ישלח את/כם מ/זה כ/שלח/ו כלה גרש יגרש את/כם מ/זה"
    },
    {
      "verse": 2,
      "text": "דבר נא ב/אזני ה/עם ו/ישאלו איש מ/את רע/הו ו/אשה מ/את רעות/ה כלי כסף ו/כלי זהב"
    },
    {
      "verse": 3,
      "text": "ו/יתן יהוה את חן ה/עם ב/עיני מצרים גם ה/איש משה גדול מאד ב/ארץ מצרים ב/עיני עבדי פרעה ו/ב/עיני ה/עם"
    },
    {
      "verse": 4,
      "text": "ו/יאמר משה כה אמר יהוה כ/חצת ה/לילה אני יוצא ב/תוך מצרים"
    },
    {
      "verse": 5,
      "text": "ו/מת כל בכור ב/ארץ מצרים מ/בכור פרעה ה/ישב על כסא/ו עד בכור ה/שפחה אשר אחר ה/רחים ו/כל בכור בהמה"
    },
    {
      "verse": 6,
      "text": "ו/היתה צעקה גדלה ב/כל ארץ מצרים אשר כמ/הו לא נהיתה ו/כמ/הו לא תסף"
    },
    {
      "verse": 7,
      "text": "ו/ל/כל בני ישראל לא יחרץ כלב לשנ/ו ל/מ/איש ו/עד בהמה למען תדעו/ן אשר יפלה יהוה בין מצרים ו/בין ישראל"
    },
    {
      "verse": 8,
      "text": "ו/ירדו כל עבדי/ך אלה אל/י ו/השתחוו ל/י ל/אמר צא אתה ו/כל ה/עם אשר ב/רגלי/ך ו/אחרי כן אצא ו/יצא מ/עם פרעה ב/חרי אף"
    },
    {
      "verse": 9,
      "text": "ו/יאמר יהוה אל משה לא ישמע אלי/כם פרעה למען רבות מופת/י ב/ארץ מצרים"
    },
    {
      "verse": 10,
      "text": "ו/משה ו/אהרן עשו את כל ה/מפתים ה/אלה ל/פני פרעה ו/יחזק יהוה את לב פרעה ו/לא שלח את בני ישראל מ/ארצ/ו"
    }
  ]
}