{
  "book": "Exodus",
  "chapter": 14,
  "language": "hebrew",
  "version": "Hebrew",
  "verses": [
    {
      "verse": 1,
      "text": "ו/ידבר יהוה אל משה ל/אמר"
    },
    {
      "verse": 2,
      "text": "דבר אל בני ישראל ו/ישבו ו/יחנו ל/פני פי החירת בין מגדל ו/בין ה/ים ל/פני בעל צפן נכח/ו תחנו על ה/ים"
    },
    {
      "verse": 3,
      "text": "ו/אמר פרעה ל/בני ישראל נבכים הם ב/ארץ סגר עלי/הם ה/מדבר"
    },
    {
      "verse": 4,
      "text": "ו/חזקתי את לב פרעה ו/רדף אחרי/הם ו/אכבדה ב/פרעה ו/ב/כל חיל/ו ו/ידעו מצרים כי אני יהוה ו/יעשו כן"
    },
    {
      "verse": 5,
      "text": "ו/יגד ל/מלך מצרים כי ברח ה/עם ו/יהפך לבב פרעה ו/עבדי/ו אל ה/עם ו/יאמרו מה זאת עשינו כי שלחנו את ישראל מ/עבד/נו"
    },
    {
      "verse": 6,
      "text": "ו/יאסר את רכב/ו ו/את עמ/ו לקח עמ/ו"
    },
    {
      "verse": 7,
      "text": "ו/יקח שש מאות רכב בחור ו/כל רכב מצרים ו/שלשם על כל/ו"
    },
    {
      "verse": 8,
      "text": "ו/יחזק יהוה את לב פרעה מלך מצרים ו/ירדף אחרי בני ישראל ו/בני ישראל יצאים ב/יד רמה"
    },
    {
      "verse": 9,
      "text": "ו/ירדפו מצרים אחרי/הם ו/ישיגו אות/ם חנים על ה/ים כל סוס רכב פרעה ו/פרשי/ו ו/חיל/ו על פי החירת ל/פני בעל צפן"
    },
    {
      "verse": 10,
      "text": "ו/פרעה הקריב ו/ישאו בני ישראל את עיני/הם ו/הנה מצרים נסע אחרי/הם ו/ייראו מאד ו/יצעקו בני ישראל אל יהוה"
    },
    {
      "verse": 11,
      "text": "ו/יאמרו אל משה ה/מ/בלי אין קברים ב/מצרים לקחת/נו ל/מות ב/מדבר מה זאת עשית ל/נו ל/הוציא/נו מ/מצרים"
    },
    {
      "verse": 12,
      "text": "ה/לא זה ה/דבר אשר דברנו אלי/ך ב/מצרים ל/אמר חדל ממ/נו ו/נעבדה את מצרים כי טוב ל/נו עבד את מצרים מ/מת/נו ב/מדבר"
    },
    {
      "verse": 13,
      "text": "ו/יאמר משה אל ה/עם אל תיראו התיצבו ו/ראו את ישועת יהוה אשר יעשה ל/כם ה/יום כי אשר ראיתם את מצרים ה/יום לא תסיפו ל/ראת/ם עוד עד עולם"
    },
    {
      "verse": 14,
      "text": "יהוה ילחם ל/כם ו/אתם תחרישו/ן"
    },
    {
      "verse": 15,
      "text": "ו/יאמר יהוה אל משה מה תצעק אל/י דבר אל בני ישראל ו/יסעו"
    },
    {
      "verse": 16,
      "text": "ו/אתה הרם את מט/ך ו/נטה את יד/ך על ה/ים ו/בקע/הו ו/יבאו בני ישראל ב/תוך ה/ים ב/יבשה"
    },
    {
      "verse": 17,
      "text": "ו/אני הנ/ני מחזק את לב מצרים ו/יבאו אחרי/הם ו/אכבדה ב/פרעה ו/ב/כל חיל/ו ב/רכב/ו ו/ב/פרשי/ו"
    },
    {
      "verse": 18,
      "text": "ו/ידעו מצרים כי אני יהוה ב/הכבד/י ב/פרעה ב/רכב/ו ו/ב/פרשי/ו"
    },
    {
      "verse": 19,
      "text": "ו/יסע מלאך ה/אלהים ה/הלך ל/פני מחנה ישראל ו/ילך מ/אחרי/הם ו/יסע עמוד ה/ענן מ/פני/הם ו/יעמד מ/אחרי/הם"
    },
    {
      "verse": 20,
      "text": "ו/יבא בין מחנה מצרים ו/בין מחנה ישראל ו/יהי ה/ענן ו/ה/חשך ו/יאר את ה/לילה ו/לא קרב זה אל זה כל ה/לילה"
    },
    {
      "verse": 21,
      "text": "ו/יט משה את יד/ו על ה/ים ו/יולך יהוה את ה/ים ב/רוח קדים עזה כל ה/לילה ו/ישם את ה/ים ל/חרבה ו/יבקעו ה/מים"
    },
    {
      "verse": 22,
      "text": "ו/יבאו בני ישראל ב/תוך ה/ים ב/יבשה ו/ה/מים ל/הם חמה מ/ימינ/ם ו/מ/שמאל/ם"
    },
    {
      "verse": 23,
      "text": "ו/ירדפו מצרים ו/יבאו אחרי/הם כל סוס פרעה רכב/ו ו/פרשי/ו אל תוך ה/ים"
    },
    {
      "verse": 24,
      "text": "ו/יהי ב/אשמרת ה/בקר ו/ישקף יהוה אל מחנה מצרים ב/עמוד אש ו/ענן ו/יהם את מחנה מצרים"
    },
    {
      "verse": 25,
      "text": "ו/יסר את אפן מרכבתי/ו ו/ינהג/הו ב/כבדת ו/יאמר מצרים אנוסה מ/פני ישראל כי יהוה נלחם ל/הם ב/מצרים"
    },
    {
      "verse": 26,
      "text": "ו/יאמר יהוה אל משה נטה את יד/ך על ה/ים ו/ישבו ה/מים על מצרים על רכב/ו ו/על פרשי/ו"
    },
    {
      "verse": 27,
      "text": "ו/יט משה את יד/ו על ה/ים ו/ישב ה/ים ל/פנות בקר ל/איתנ/ו ו/מצרים נסים ל/קראת/ו ו/ינער יהוה את מצרים ב/תוך ה/ים"
    },
    {
      "verse": 28,
      "text": "ו/ישבו ה/מים ו/יכסו את ה/רכב ו/את ה/פרשים ל/כל חיל פרעה ה/באים אחרי/הם ב/ים לא נשאר ב/הם עד אחד"
    },
    {
      "verse": 29,
      "text": "ו/בני ישראל הלכו ב/יבשה ב/תוך ה/ים ו/ה/מים ל/הם חמה מ/ימינ/ם ו/מ/שמאל/ם"
    },
    {
      "verse": 30,
      "text": "ו/יושע יהוה ב/יום ה/הוא את ישראל מ/יד מצרים ו/ירא ישראל את מצרים מת על שפת ה/ים"
    },
    {
      "verse": 31,
      "text": "ו/ירא ישראל את ה/יד ה/גדלה אשר עשה יהוה ב/מצרים ו/ייראו ה/עם את יהוה ו/יאמינו ב/יהוה ו/ב/משה עבד/ו"
    }
  ]
}